scallop/__main__.py
scallop/cli.py
scallop/sea.py
scallop/stomp.py
node_sea_scallop-0.1.2.dist-info/entry_points.txt
node_sea_scallop-0.1.2.dist-info/LICENSE
node_sea_scallop-0.1.2.dist-info/METADATA
node_sea_scallop-0.1.2.dist-info/WHEEL
node_sea_scallop-0.1.2.dist-info/RECORD
