Metadata-Version: 2.3
Name: node-sea-scallop
Version: 0.1.2
Summary: Scallop is a multi-tool for unpacking, repacking, and script stomping nodejs single executable applications (SEA)s.
License: MIT
Keywords: node,nodejs,sea,single,file,executable,unpack,repack,script,stomp,javascript,scallop
Author: Darius Houle
Author-email: darius@x64.ooo
Requires-Python: >=3.11
Classifier: License :: OSI Approved :: MIT License
Classifier: Programming Language :: Python :: 3
Classifier: Programming Language :: Python :: 3.11
Classifier: Programming Language :: Python :: 3.12
Classifier: Programming Language :: Python :: 3.13
Requires-Dist: lief (>=0.16.5,<0.17.0)
Requires-Dist: typer (>=0.15.2,<0.16.0)
Project-URL: Homepage, https://github.com/dariushoule/node-sea-scallop
Project-URL: Issues, https://github.com/dariushoule/node-sea-scallop/issues
Project-URL: Repository, https://github.com/dariushoule/node-sea-scallop
